tonic_ollama_client/__init__.py
tonic_ollama_client-1.0.3.dist-info/METADATA
tonic_ollama_client-1.0.3.dist-info/WHEEL
tonic_ollama_client-1.0.3.dist-info/top_level.txt
tonic_ollama_client-1.0.3.dist-info/RECORD
