Metadata-Version: 2.4
Name: tonic-ollama-client
Version: 1.0.3
Summary: A very simple ollama client for our tonic software.
Author-email: Tonic Team <info@tonic-ai.com>
Project-URL: Homepage, https://github.com/FinTechTonic/tonic-ollama-client
Project-URL: Bug Tracker, https://github.com/FinTechTonic/tonic-ollama-client/issues
Keywords: ollama,client,tonic,ai,software,development
Classifier: Development Status :: 3 - Alpha
Classifier: Intended Audience :: Developers
Classifier: Programming Language :: Python :: 3
Classifier: Programming Language :: Python :: 3.11
Classifier: Programming Language :: Python :: 3.12
Classifier: Programming Language :: Python :: 3.13
Classifier: Programming Language :: Python :: 3.14
Classifier: Topic :: Software Development :: Libraries :: Python Modules
Requires-Python: >=3.11
Requires-Dist: ollama>=0.5.1
Requires-Dist: rich>=14.0.0
Requires-Dist: tenacity>=9.1.2
Requires-Dist: questionary>=2.0.1
Requires-Dist: tiktoken>=0.9.0
Provides-Extra: dev
Requires-Dist: pytest>=7.0.0; extra == "dev"
Requires-Dist: pytest-asyncio>=0.21.0; extra == "dev"
Requires-Dist: pydantic>=2.0.0; extra == "dev"
Requires-Dist: black>=23.0.0; extra == "dev"
Requires-Dist: ruff>=0.0.292; extra == "dev"
Requires-Dist: twine>=4.0.0; extra == "dev"
